odoo/addons/account_invoice_edifact/README.rst
odoo/addons/account_invoice_edifact/__init__.py
odoo/addons/account_invoice_edifact/__manifest__.py
odoo/addons/account_invoice_edifact/demo/data_demo.xml
odoo/addons/account_invoice_edifact/i18n/account_invoice_edifact.pot
odoo/addons/account_invoice_edifact/i18n/es.po
odoo/addons/account_invoice_edifact/i18n/it.po
odoo/addons/account_invoice_edifact/models/__init__.py
odoo/addons/account_invoice_edifact/models/account_move.py
odoo/addons/account_invoice_edifact/readme/CONTRIBUTORS.rst
odoo/addons/account_invoice_edifact/readme/CREDITS.rst
odoo/addons/account_invoice_edifact/readme/DESCRIPTION.rst
odoo/addons/account_invoice_edifact/static/description/icon.png
odoo/addons/account_invoice_edifact/static/description/index.html
odoo/addons/account_invoice_edifact/tests/__init__.py
odoo/addons/account_invoice_edifact/tests/test_account_move.py
odoo_addon_account_invoice_edifact-16.0.1.0.0.7.dist-info/METADATA
odoo_addon_account_invoice_edifact-16.0.1.0.0.7.dist-info/WHEEL
odoo_addon_account_invoice_edifact-16.0.1.0.0.7.dist-info/top_level.txt
odoo_addon_account_invoice_edifact-16.0.1.0.0.7.dist-info/RECORD
