Metadata-Version: 2.1
Name: odoo-addon-account-invoice-edifact
Version: 16.0.1.0.0.7
Summary: Generate customer invoices with EDIFACT/D96A format
Home-page: https://github.com/OCA/edi
Author: Camptocamp, Odoo Community Association (OCA)
Author-email: support@odoo-community.org
License: AGPL-3
Platform: UNKNOWN
Classifier: Programming Language :: Python
Classifier: Framework :: Odoo
Classifier: Framework :: Odoo :: 16.0
Classifier: License :: OSI Approved :: GNU Affero General Public License v3
Classifier: Development Status :: 3 - Alpha
Requires-Python: >=3.10
Requires-Dist: odoo-addon-base-edifact <16.1dev,>=16.0dev
Requires-Dist: odoo <16.1dev,>=16.0a
